alibabacloud_ehpc20180412/__init__.py
alibabacloud_ehpc20180412/client.py
alibabacloud_ehpc20180412/models.py
alibabacloud_ehpc20180412-4.0.0.dist-info/LICENSE
alibabacloud_ehpc20180412-4.0.0.dist-info/METADATA
alibabacloud_ehpc20180412-4.0.0.dist-info/WHEEL
alibabacloud_ehpc20180412-4.0.0.dist-info/top_level.txt
alibabacloud_ehpc20180412-4.0.0.dist-info/RECORD
